tmuxp/__about__.py
tmuxp/__init__.py
tmuxp/_compat.py
tmuxp/exc.py
tmuxp/log.py
tmuxp/plugin.py
tmuxp/shell.py
tmuxp/types.py
tmuxp/util.py
tmuxp/_internal/__init__.py
tmuxp/_internal/colors.py
tmuxp/_internal/config_reader.py
tmuxp/_internal/private_path.py
tmuxp/_internal/types.py
tmuxp/cli/__init__.py
tmuxp/cli/_colors.py
tmuxp/cli/_formatter.py
tmuxp/cli/_output.py
tmuxp/cli/convert.py
tmuxp/cli/debug_info.py
tmuxp/cli/edit.py
tmuxp/cli/freeze.py
tmuxp/cli/import_config.py
tmuxp/cli/load.py
tmuxp/cli/ls.py
tmuxp/cli/search.py
tmuxp/cli/shell.py
tmuxp/cli/utils.py
tmuxp/workspace/__init__.py
tmuxp/workspace/builder.py
tmuxp/workspace/constants.py
tmuxp/workspace/finders.py
tmuxp/workspace/freezer.py
tmuxp/workspace/importers.py
tmuxp/workspace/loader.py
tmuxp/workspace/validation.py
tmuxp-1.64.0.dist-info/METADATA
tmuxp-1.64.0.dist-info/WHEEL
tmuxp-1.64.0.dist-info/entry_points.txt
tmuxp-1.64.0.dist-info/licenses/LICENSE
tmuxp-1.64.0.dist-info/RECORD
