Metadata-Version: 2.4
Name: tmuxp
Version: 1.64.0
Summary: Session manager for tmux, which allows users to save and load tmux sessions through simple configuration files.
Project-URL: Bug Tracker, https://github.com/tmux-python/tmuxp/issues
Project-URL: Documentation, https://tmuxp.git-pull.com
Project-URL: Repository, https://github.com/tmux-python/tmuxp
Project-URL: Changes, https://github.com/tmux-python/tmuxp/blob/master/CHANGES
Author-email: Tony Narlock <tony@git-pull.com>
License: MIT
License-File: LICENSE
Keywords: ncurses,session manager,terminal,tmux
Classifier: Development Status :: 5 - Production/Stable
Classifier: Environment :: Web Environment
Classifier: Intended Audience :: Developers
Classifier: License :: OSI Approved :: MIT License
Classifier: Operating System :: MacOS :: MacOS X
Classifier: Operating System :: POSIX
Classifier: Programming Language :: Python
Classifier: Programming Language :: Python :: 3.10
Classifier: Programming Language :: Python :: 3.11
Classifier: Programming Language :: Python :: 3.12
Classifier: Programming Language :: Python :: 3.13
Classifier: Programming Language :: Python :: 3.14
Classifier: Programming Language :: Python :: Implementation :: PyPy
Classifier: Topic :: System :: Shells
Classifier: Topic :: Utilities
Requires-Python: <4.0,>=3.10
Requires-Dist: colorama>=0.3.9
Requires-Dist: libtmux~=0.53.0
Requires-Dist: pyyaml>=6.0
